context_cache/__init__.py
context_cache/context.py
context_cache/decorators.py
context_cache/middleware.py
example/__init__.py
example/manage.py
example/urls.py
example/wsgi.py
example/apps/__init__.py
example/apps/app/__init__.py
example/apps/app/views.py
example/apps/app/tests/__init__.py
example/settings/__init__.py
example/settings/base.py
example/settings/settings.py
skip_django_context_cache-0.0.2.1.dist-info/LICENSE
skip_django_context_cache-0.0.2.1.dist-info/METADATA
skip_django_context_cache-0.0.2.1.dist-info/WHEEL
skip_django_context_cache-0.0.2.1.dist-info/top_level.txt
skip_django_context_cache-0.0.2.1.dist-info/RECORD
