Metadata-Version: 2.1
Name: skip-django-context-cache
Version: 0.0.2.1
Summary: Django context cache library.
Home-page: https://github.com/skip-pay/django-context-cache
Author: Lubos Matl
Author-email: matllubos@gmail.com
License: MIT
Keywords: django,cache,request cache
Classifier: Development Status :: 3 - Alpha
Classifier: Environment :: Web Environment
Classifier: Framework :: Django
Classifier: Intended Audience :: Developers
Classifier: Intended Audience :: End Users/Desktop
Classifier: License :: OSI Approved :: MIT License
Classifier: Natural Language :: Czech
Classifier: Operating System :: OS Independent
Classifier: Programming Language :: Python
Classifier: Topic :: Internet :: WWW/HTTP :: Dynamic Content
Classifier: Topic :: Internet :: WWW/HTTP :: Site Management
License-File: LICENSE
Requires-Dist: django (>=2.0)
